road_flood_risk_map/__init__.py
road_flood_risk_map/common.py
road_flood_risk_map/road_flood_risk_map.py
road_flood_risk_map-0.1.2.dist-info/licenses/LICENSE
road_flood_risk_map-0.1.2.dist-info/METADATA
road_flood_risk_map-0.1.2.dist-info/WHEEL
road_flood_risk_map-0.1.2.dist-info/entry_points.txt
road_flood_risk_map-0.1.2.dist-info/top_level.txt
road_flood_risk_map-0.1.2.dist-info/RECORD
