Metadata-Version: 2.4
Name: road-flood-risk-map
Version: 0.1.2
Summary: A python package for doing flood risk analysis of roads.
Author-email: Martin Arrogante <arrogantemartin@gmail.com>
License: MIT License
Project-URL: Homepage, https://github.com/marts-dev/road-flood-risk-map
Keywords: road-flood-risk-map
Classifier: Intended Audience :: Developers
Classifier: License :: OSI Approved :: MIT License
Classifier: Natural Language :: English
Classifier: Programming Language :: Python :: 3.10
Classifier: Programming Language :: Python :: 3.11
Classifier: Programming Language :: Python :: 3.12
Requires-Python: >=3.10
License-File: LICENSE
Requires-Dist: numpy
Requires-Dist: xarray
Requires-Dist: osmnx
Requires-Dist: rasterio
Requires-Dist: geopandas
Requires-Dist: leafmap
Requires-Dist: localtileserver
Requires-Dist: geemap
Requires-Dist: earthengine-api
Requires-Dist: whitebox-workflows
Requires-Dist: ipywidgets
Provides-Extra: all
Requires-Dist: road-flood-risk-map[extra]; extra == "all"
Provides-Extra: extra
Requires-Dist: pandas; extra == "extra"
Dynamic: license-file
